mars_patcher/__init__.py
mars_patcher/__main__.py
mars_patcher/cli.py
mars_patcher/color_spaces.py
mars_patcher/common_types.py
mars_patcher/compress.py
mars_patcher/credits.py
mars_patcher/item_messages.py
mars_patcher/level_edits.py
mars_patcher/minimap.py
mars_patcher/minimap_tile_creator.py
mars_patcher/palette.py
mars_patcher/patcher.py
mars_patcher/patching.py
mars_patcher/py.typed
mars_patcher/random_enemies.py
mars_patcher/random_palettes.py
mars_patcher/rom.py
mars_patcher/room_entry.py
mars_patcher/text.py
mars_patcher/tileset.py
mars_patcher/titlescreen_text.py
mars_patcher/version.py
mars_patcher/__pyinstaller/__init__.py
mars_patcher/__pyinstaller/hook-mars_patcher.py
mars_patcher/constants/credits.py
mars_patcher/constants/door_types.py
mars_patcher/constants/enemies.py
mars_patcher/constants/game_data.py
mars_patcher/constants/minimap_tiles.py
mars_patcher/mf/auto_generated_types.py
mars_patcher/mf/connections.py
mars_patcher/mf/credits.py
mars_patcher/mf/data.py
mars_patcher/mf/door_locks.py
mars_patcher/mf/item_patcher.py
mars_patcher/mf/locations.py
mars_patcher/mf/misc_patches.py
mars_patcher/mf/navigation_text.py
mars_patcher/mf/patcher.py
mars_patcher/mf/room_names.py
mars_patcher/mf/starting.py
mars_patcher/mf/constants/__init__.py
mars_patcher/mf/constants/credits_lines.py
mars_patcher/mf/constants/enemies.py
mars_patcher/mf/constants/game_data.py
mars_patcher/mf/constants/items.py
mars_patcher/mf/constants/main_hub_numbers.py
mars_patcher/mf/constants/minimap_tiles.py
mars_patcher/mf/constants/palettes.py
mars_patcher/mf/constants/reserved_space.py
mars_patcher/mf/constants/sprites.py
mars_patcher/mf/data/base_minimap_edits.json
mars_patcher/mf/data/char_map_mf.json
mars_patcher/mf/data/locations.json
mars_patcher/mf/data/main_hub.gfx.lz
mars_patcher/mf/data/main_hub_tilemap.bin
mars_patcher/mf/data/schema.json
mars_patcher/mf/data/patches/mf_u/asm/.gitignore
mars_patcher/mf/data/patches/mf_u/asm/accessibility.ips
mars_patcher-0.10.0.dist-info/licenses/LICENSE
mars_patcher-0.10.0.dist-info/METADATA
mars_patcher-0.10.0.dist-info/WHEEL
mars_patcher-0.10.0.dist-info/entry_points.txt
mars_patcher-0.10.0.dist-info/top_level.txt
mars_patcher-0.10.0.dist-info/RECORD
