Metadata-Version: 2.4
Name: mars_patcher
Version: 0.10.0
Summary: An open source randomizer patcher for Metroid Fusion.
Author: biospark
License:                     GNU GENERAL PUBLIC LICENSE
Project-URL: Repository, https://github.com/MetroidAdvRandomizerSystem/mars-patcher
Classifier: Programming Language :: Python :: 3
Classifier: License :: OSI Approved :: GNU General Public License v3 (GPLv3)
Classifier: Development Status :: 3 - Alpha
Classifier: Programming Language :: Python :: 3.10
Requires-Python: >=3.10
License-File: LICENSE
Requires-Dist: jsonschema
Requires-Dist: frozendict
Requires-Dist: typing-extensions
Provides-Extra: tooling
Requires-Dist: requests; extra == "tooling"
Provides-Extra: test
Requires-Dist: pytest; extra == "test"
Requires-Dist: pytest-cov; extra == "test"
Requires-Dist: pytest-mock; extra == "test"
Provides-Extra: typing
Requires-Dist: mypy; extra == "typing"
Requires-Dist: types-requests; extra == "typing"
Requires-Dist: types-pyinstaller; extra == "typing"
Requires-Dist: types-jsonschema; extra == "typing"
Requires-Dist: pre-commit; extra == "typing"
Dynamic: license-file
